README.rst
setup.py
biometal/__init__.py
biometal/charges.py
biometal/hydrophobicity.py
biometal/templates.py
biometal.egg-info/PKG-INFO
biometal.egg-info/SOURCES.txt
biometal.egg-info/dependency_links.txt
biometal.egg-info/requires.txt
biometal.egg-info/top_level.txt