Metadata-Version: 1.1
Name: biometal
Version: 0.1.0
Summary: Tools for dealing with metal binding sites.
Home-page: https://biometal.samireland.com
Author: Sam Ireland
Author-email: mail@samireland.com
License: MIT
Keywords: chemistry bioinformatics proteins biochemistry metals
Platform: UNKNOWN
Classifier: Development Status :: 4 - Beta
Classifier: Intended Audience :: Science/Research
Classifier: License :: OSI Approved :: MIT License
Classifier: Topic :: Scientific/Engineering :: Chemistry
Classifier: Programming Language :: Python :: 3
Classifier: Programming Language :: Python :: 3.5
Classifier: Programming Language :: Python :: 3.6
